tsuki/__init__.py
tsuki/tsuki.py
tsuki-0.1.dist-info/LICENCE
tsuki-0.1.dist-info/METADATA
tsuki-0.1.dist-info/WHEEL
tsuki-0.1.dist-info/top_level.txt
tsuki-0.1.dist-info/RECORD
